streamlit_tfx/__init__.py
streamlit_tfx/visualization.py
streamlit_tfx-22.6.4.dev0.dist-info/WHEEL
streamlit_tfx-22.6.4.dev0.dist-info/METADATA
streamlit_tfx-22.6.4.dev0.dist-info/RECORD
