Metadata-Version: 2.1
Name: streamlit-tfx
Version: 22.6.4.dev0
Summary: TensorFlow Extended visualizers for Streamlit apps
Home-page: https://github.com/codesue/streamlit-tfx
Keywords: streamlit,tfx,visualization
Author: Suzen Fylke
Author-email: codesue@users.noreply.github.com
Requires-Python: >=3.9,<3.10
Classifier: Intended Audience :: Developers
Classifier: Programming Language :: Python :: 3
Classifier: Programming Language :: Python :: 3.9
Classifier: Topic :: Scientific/Engineering :: Artificial Intelligence
Classifier: Topic :: Scientific/Engineering :: Visualization
Requires-Dist: ipywidgets (>=7.7.0,<8.0.0)
Requires-Dist: streamlit (>=1.9.2,<2.0.0)
Requires-Dist: tfx (>=1.8.0,<2.0.0)
Project-URL: Repository, https://github.com/codesue/streamlit-tfx
